[
  {
    "Author": "Herculezz, erdelf",
    "Name": "AutoDuty",
    "InternalName": "AutoDuty",
    "AssemblyVersion": "0.0.0.294",
    "Description": "自动运行副本的插件，支持信任、副本支援、小队、多变术副本和普通副本。需要 BossMod、vnavmesh 和一个自动技能插件（Wrath Combo、BossMod AutoRotation 或 RotationSolverReborn）",
    "ApplicableVersion": "any",
    "RepoUrl": "https://github.com/mulongsheng/puppys-plugins",
    "DalamudApiLevel": 12,
    "LoadRequiredState": 0,
    "LoadSync": false,
    "CanUnloadAsync": false,
    "LoadPriority": 0,
    "ImageUrls": [
      "https://s3.puni.sh/media/plugin/54/image-15l1o9gf3yg.png",
      "https://s3.puni.sh/media/plugin/54/image-gc84lu4pdpb.png",
      "https://s3.puni.sh/media/plugin/54/image-vkvtqki3ggh.png",
      "https://s3.puni.sh/media/plugin/54/image-pw9lcsan22.png",
      "https://s3.puni.sh/media/plugin/54/image-5lu04i95hz8.png"
    ],
    "IconUrl": "https://s3.puni.sh/media/plugin/54/icon-15ug2vnr9m1.png",
    "Punchline": "自动副本",
    "AcceptsFeedback": true,
    "DownloadLinkInstall": "https://raw.githubusercontent.com/mulongsheng/puppys-plugins/main/plugins/AutoDuty/latest.zip",
    "DownloadLinkUpdate": "https://raw.githubusercontent.com/mulongsheng/puppys-plugins/main/plugins/AutoDuty/latest.zip",
    "DownloadLinkTesting": "https://raw.githubusercontent.com/mulongsheng/puppys-plugins/main/plugins/AutoDuty/latest.zip"
  },
  {
    "Author": "NightmareXIV",
    "Name": "Lifestream",
    "InternalName": "Lifestream",
    "AssemblyVersion": "2.5.2.1",
    "Description": "一键传送至任何世界或以太网目的地，在区域地图中点击以太碎片即可传送",
    "ApplicableVersion": "any",
    "RepoUrl": "https://github.com/mulongsheng/puppys-plugins",
    "DalamudApiLevel": 12,
    "LoadRequiredState": 0,
    "LoadSync": false,
    "CanUnloadAsync": false,
    "LoadPriority": 0,
    "IconUrl": "https://raw.githubusercontent.com/NightmareXIV/MyDalamudPlugins/main/icons/lifestream.png",
    "Punchline": "加速以太网旅行和世界切换的插件。",
    "AcceptsFeedback": false,
    "DownloadLinkInstall": "https://raw.githubusercontent.com/mulongsheng/puppys-plugins/main/plugins/Lifestream/latest.zip",
    "DownloadLinkUpdate": "https://raw.githubusercontent.com/mulongsheng/puppys-plugins/main/plugins/Lifestream/latest.zip",
    "DownloadLinkTesting": "https://raw.githubusercontent.com/mulongsheng/puppys-plugins/main/plugins/Lifestream/latest.zip"
  },
  {
    "Author": "Liza Carvelli",
    "Name": "Questionable",
    "InternalName": "Questionable",
    "AssemblyVersion": "5.23",
    "Description": "一个自动任务助手插件，尽可能为您自动完成任务。使用 navmesh 自动行走至所有任务路径点。必需插件：vnavmesh、TextAdvance、Lifestream",
    "ApplicableVersion": "any",
    "RepoUrl": "https://github.com/mulongsheng/puppys-plugins",
    "Tags": [
      "quests",
      "msq"
    ],
    "DalamudApiLevel": 12,
    "LoadRequiredState": 0,
    "LoadSync": false,
    "CanUnloadAsync": false,
    "LoadPriority": 0,
    "IconUrl": "https://raw.githubusercontent.com/mulongsheng/puppys-plugins/main/icons/Questionable.png",
    "Punchline": "自动任务助手插件。",
    "AcceptsFeedback": true,
    "DownloadLinkInstall": "https://raw.githubusercontent.com/mulongsheng/puppys-plugins/main/plugins/Questionable/latest.zip",
    "DownloadLinkUpdate": "https://raw.githubusercontent.com/mulongsheng/puppys-plugins/main/plugins/Questionable/latest.zip",
    "DownloadLinkTesting": "https://raw.githubusercontent.com/mulongsheng/puppys-plugins/main/plugins/Questionable/latest.zip"
  },
  {
    "Author": "NightmareXIV",
    "Name": "Splatoon",
    "InternalName": "Splatoon",
    "AssemblyVersion": "3.7.0.4",
    "Description": "Splatoon 是一个强大的辅助工具。它通过自定义标记系统革新了游戏体验，提供创建无限分组标记、标签和角色指示器的能力。",
    "ApplicableVersion": "any",
    "RepoUrl": "https://github.com/mulongsheng/puppys-plugins",
    "Tags": [
      "Utility",
      "Accessibility"
    ],
    "DalamudApiLevel": 12,
    "LoadRequiredState": 0,
    "LoadSync": false,
    "CanUnloadAsync": false,
    "LoadPriority": 0,
    "IconUrl": "https://raw.githubusercontent.com/mulongsheng/puppys-plugins/main/icons/Splatoon.png",
    "Punchline": "重新定义 FFXIV 导航，提供无限精确的自定义标记。",
    "AcceptsFeedback": true,
    "DownloadLinkInstall": "https://raw.githubusercontent.com/mulongsheng/puppys-plugins/main/plugins/Splatoon/latest.zip",
    "DownloadLinkUpdate": "https://raw.githubusercontent.com/mulongsheng/puppys-plugins/main/plugins/Splatoon/latest.zip",
    "DownloadLinkTesting": "https://raw.githubusercontent.com/mulongsheng/puppys-plugins/main/plugins/Splatoon/latest.zip"
  },
  {
    "Author": "NightmareXIV",
    "Name": "TextAdvance",
    "InternalName": "TextAdvance",
    "AssemblyVersion": "3.2.4.3",
    "Description": "任务速通辅助工具。自动跳过对话框并确认跳过动画。",
    "ApplicableVersion": "any",
    "RepoUrl": "https://github.com/mulongsheng/puppys-plugins",
    "DalamudApiLevel": 12,
    "LoadRequiredState": 0,
    "LoadSync": false,
    "CanUnloadAsync": false,
    "LoadPriority": 0,
    "IconUrl": "https://raw.githubusercontent.com/NightmareXIV/TextAdvance/master/TextAdvance/images/icon.png",
    "Punchline": "任务速通辅助工具。自动跳过对话框并确认跳过动画",
    "AcceptsFeedback": true,
    "DownloadLinkInstall": "https://raw.githubusercontent.com/mulongsheng/puppys-plugins/main/plugins/TextAdvance/latest.zip",
    "DownloadLinkUpdate": "https://raw.githubusercontent.com/mulongsheng/puppys-plugins/main/plugins/TextAdvance/latest.zip",
    "DownloadLinkTesting": "https://raw.githubusercontent.com/mulongsheng/puppys-plugins/main/plugins/TextAdvance/latest.zip"
  },
  {
    "Author": "The Combat Reborn Team",
    "Name": "Bossmod Reborn",
    "InternalName": "BossModReborn",
    "AssemblyVersion": "0.0.0.0",
    "Description": "简化 Boss 战的综合工具集。",
    "ApplicableVersion": "any",
    "RepoUrl": "https://github.com/mulongsheng/puppys-plugins",
    "DalamudApiLevel": 12,
    "LoadRequiredState": 0,
    "LoadSync": false,
    "CanUnloadAsync": false,
    "LoadPriority": 0,
    "ImageUrls": [
      "https://raw.githubusercontent.com/awgil/ffxiv_bossmod/master/Data/image1.png",
      "https://raw.githubusercontent.com/awgil/ffxiv_bossmod/master/Data/image2.png",
      "https://raw.githubusercontent.com/awgil/ffxiv_bossmod/master/Data/image3.png"
    ],
    "IconUrl": "https://raw.githubusercontent.com/FFXIV-CombatReborn/RebornAssets/main/IconAssets/BMR_Icon.png",
    "Punchline": "不再搞砸团队机制",
    "AcceptsFeedback": true,
    "DownloadLinkInstall": "https://raw.githubusercontent.com/mulongsheng/puppys-plugins/main/plugins/BossModReborn/latest.zip",
    "DownloadLinkUpdate": "https://raw.githubusercontent.com/mulongsheng/puppys-plugins/main/plugins/BossModReborn/latest.zip",
    "DownloadLinkTesting": "https://raw.githubusercontent.com/mulongsheng/puppys-plugins/main/plugins/BossModReborn/latest.zip"
  },
  {
    "Author": "veyn",
    "Name": "vnavmesh",
    "InternalName": "vnavmesh",
    "AssemblyVersion": "0.0.0.0",
    "Description": "自动导航移动工具，智能地带领角色在世界中穿行，巧妙地避开所有障碍物。",
    "ApplicableVersion": "any",
    "RepoUrl": "https://github.com/mulongsheng/puppys-plugins",
    "DalamudApiLevel": 12,
    "LoadRequiredState": 0,
    "LoadSync": false,
    "CanUnloadAsync": false,
    "LoadPriority": 0,
    "IconUrl": "https://raw.githubusercontent.com/awgil/ffxiv_navmesh/8dab2e675e51a03b1827d94e77616a8144892a72/icon2.png",
    "Punchline": "自动导航移动！",
    "AcceptsFeedback": true,
    "DownloadLinkInstall": "https://raw.githubusercontent.com/mulongsheng/puppys-plugins/main/plugins/vnavmesh/latest.zip",
    "DownloadLinkUpdate": "https://raw.githubusercontent.com/mulongsheng/puppys-plugins/main/plugins/vnavmesh/latest.zip",
    "DownloadLinkTesting": "https://raw.githubusercontent.com/mulongsheng/puppys-plugins/main/plugins/vnavmesh/latest.zip"
  }
]
